lasso/__init__.py
lasso/html/REQUIREMENTS.html.template
lasso/html/__init__.py
lasso/html/md_to_html.py
lasso/requirements/VERSION.txt
lasso/requirements/__init__.py
lasso/requirements/generate_requirements.py
lasso/requirements/requirements.py
lasso/tags/__init__.py
lasso/tags/tags.py
lasso_requirements-1.1.0.dist-info/licenses/LICENSE.md
lasso_requirements-1.1.0.dist-info/licenses/NOTICE.txt
lasso_requirements-1.1.0.dist-info/METADATA
lasso_requirements-1.1.0.dist-info/WHEEL
lasso_requirements-1.1.0.dist-info/entry_points.txt
lasso_requirements-1.1.0.dist-info/top_level.txt
lasso_requirements-1.1.0.dist-info/zip-safe
lasso_requirements-1.1.0.dist-info/RECORD
