Metadata-Version: 2.4
Name: lasso.requirements
Version: 1.1.0
Summary: Requirements report generation for the Planetary Data System
Home-page: https://github.com/NASA-PDS/lasso-requirements
Download-URL: https://github.com/NASA-PDS/lasso-requirements/releases/
Author: PDS
Author-email: pds_operator@jpl.nasa.gov
License: apache-2.0
Keywords: pds,planetary data,ci,automation,requirements,reporting
Classifier: Programming Language :: Python :: 3
Classifier: Programming Language :: Python :: 3.13
Classifier: Operating System :: OS Independent
Requires-Python: >=3.13
License-File: LICENSE.md
License-File: NOTICE.txt
Requires-Dist: emoji~=2.14.1
Requires-Dist: github3.py==4.0.1
Requires-Dist: jinja2~=3.1.6
Requires-Dist: markdown2~=2.5.4
Requires-Dist: mdutils~=1.8.0
Requires-Dist: packaging~=25.0
Provides-Extra: dev
Requires-Dist: flake8~=7.3.0; extra == "dev"
Requires-Dist: flake8-bugbear~=24.12.12; extra == "dev"
Requires-Dist: flake8-docstrings~=1.7.0; extra == "dev"
Requires-Dist: pep8-naming~=0.13.3; extra == "dev"
Requires-Dist: mypy~=1.14.1; extra == "dev"
Requires-Dist: pydocstyle~=6.3.0; extra == "dev"
Requires-Dist: coverage~=7.3.0; extra == "dev"
Requires-Dist: pytest~=7.4.0; extra == "dev"
Requires-Dist: pytest-cov~=4.1.0; extra == "dev"
Requires-Dist: pytest-watch~=4.2.0; extra == "dev"
Requires-Dist: pytest-xdist~=3.3.1; extra == "dev"
Requires-Dist: pre-commit~=3.3.3; extra == "dev"
Requires-Dist: sphinx~=8.2.3; extra == "dev"
Requires-Dist: sphinx-rtd-theme~=3.0.2; extra == "dev"
Requires-Dist: tox~=4.11.0; extra == "dev"
Dynamic: download-url
Dynamic: license-file
